[{"inputs": [{"type": "uint256", "name": "a"}, {"type": "uint256", "name": "b"}], "constant": true, "name": "safeAdd", "outputs": [{"type": "uint256", "name": "c"}], "stateMutability": "pure", "payable": false, "type": "function"}, {"inputs": [{"type": "uint256", "name": "a"}, {"type": "uint256", "name": "b"}, {"type": "string", "name": "s"}], "constant": true, "name": "safeSubR", "outputs": [{"type": "uint256", "name": "c"}], "stateMutability": "pure", "payable": false, "type": "function"}, {"inputs": [{"type": "uint256", "name": "a"}, {"type": "uint256", "name": "b"}], "constant": true, "name": "safeSub", "outputs": [{"type": "uint256", "name": "c"}], "stateMutability": "pure", "payable": false, "type": "function"}, {"inputs": [{"type": "uint256", "name": "a"}, {"type": "uint256", "name": "b"}], "constant": true, "name": "safeMul", "outputs": [{"type": "uint256", "name": "c"}], "stateMutability": "pure", "payable": false, "type": "function"}, {"inputs": [{"type": "uint256", "name": "a"}, {"type": "uint256", "name": "b"}], "constant": true, "name": "safeDiv", "outputs": [{"type": "uint256", "name": "c"}], "stateMutability": "pure", "payable": false, "type": "function"}, {"inputs": [{"type": "uint256", "name": "a"}, {"type": "uint256", "name": "b"}, {"type": "string", "name": "s"}], "constant": true, "name": "safeDivR", "outputs": [{"type": "uint256", "name": "c"}], "stateMutability": "pure", "payable": false, "type": "function"}]