[{"inputs": [], "constant": true, "name": "erc20_token_addr", "outputs": [{"type": "address", "name": ""}], "stateMutability": "view", "payable": false, "type": "function"}, {"inputs": [], "constant": true, "name": "owner", "outputs": [{"type": "address", "name": ""}], "stateMutability": "view", "payable": false, "type": "function"}, {"inputs": [], "constant": true, "name": "token_name", "outputs": [{"type": "string", "name": ""}], "stateMutability": "view", "payable": false, "type": "function"}, {"inputs": [], "constant": true, "name": "trustlist", "outputs": [{"type": "address", "name": ""}], "stateMutability": "view", "payable": false, "type": "function"}, {"inputs": [{"type": "address", "name": "newOwner"}], "constant": false, "name": "transferOwnership", "outputs": [], "stateMutability": "nonpayable", "payable": false, "type": "function"}, {"stateMutability": "nonpayable", "inputs": [{"type": "string", "name": "name"}, {"type": "address", "name": "token_contract"}, {"type": "address", "name": "_tlist"}], "type": "constructor", "payable": false}, {"stateMutability": "payable", "payable": true, "type": "fallback"}, {"inputs": [{"indexed": false, "type": "address", "name": "to"}, {"indexed": false, "type": "uint256", "name": "amount"}], "type": "event", "name": "withdraw_token", "anonymous": false}, {"inputs": [{"indexed": false, "type": "address", "name": "to"}, {"indexed": false, "type": "uint256", "name": "amount"}], "type": "event", "name": "issue_token", "anonymous": false}, {"inputs": [{"indexed": false, "type": "uint256", "name": "v"}], "type": "event", "name": "RecvETH", "anonymous": false}, {"inputs": [{"indexed": true, "type": "address", "name": "_token"}, {"indexed": true, "type": "address", "name": "_to"}, {"indexed": false, "type": "uint256", "name": "_amount"}], "type": "event", "name": "ClaimedTokens", "anonymous": false}, {"inputs": [{"indexed": true, "type": "address", "name": "previousOwner"}, {"indexed": true, "type": "address", "name": "newOwner"}], "type": "event", "name": "OwnershipTransferred", "anonymous": false}, {"inputs": [{"type": "address", "name": "_token"}, {"type": "address", "name": "to"}], "constant": false, "name": "claimStdTokens", "outputs": [], "stateMutability": "nonpayable", "payable": false, "type": "function"}, {"inputs": [], "constant": false, "name": "balance", "outputs": [{"type": "uint256", "name": ""}], "stateMutability": "nonpayable", "payable": false, "type": "function"}, {"inputs": [], "constant": true, "name": "token", "outputs": [{"type": "address", "name": ""}, {"type": "string", "name": ""}], "stateMutability": "view", "payable": false, "type": "function"}, {"inputs": [{"type": "address", "name": "to"}, {"type": "uint256", "name": "tokens"}], "constant": false, "name": "transfer", "outputs": [{"type": "bool", "name": "success"}], "stateMutability": "nonpayable", "payable": false, "type": "function"}, {"inputs": [{"type": "address", "name": "_to"}, {"type": "uint256", "name": "_amount"}], "constant": false, "name": "issue", "outputs": [{"type": "bool", "name": "success"}], "stateMutability": "nonpayable", "payable": false, "type": "function"}]